prompt_craft_kit/__init__.py
prompt_craft_kit/_default_loaders.py
prompt_craft_kit/_wrapper_styles.py
prompt_craft_kit/exceptions.py
prompt_craft_kit/file_type.py
prompt_craft_kit/prompt_helpers.py
prompt_craft_kit/prompt_loader.py
prompt_craft_kit/py.typed
prompt_craft_kit/static_descriptor.py
prompt_craft_kit/static_loader.py
prompt_craft_kit/utils.py
prompt_craft_kit-0.1.2.dist-info/LICENSE
prompt_craft_kit-0.1.2.dist-info/METADATA
prompt_craft_kit-0.1.2.dist-info/WHEEL
prompt_craft_kit-0.1.2.dist-info/RECORD
