Metadata-Version: 2.3
Name: prompt-craft-kit
Version: 0.1.2
Summary: A powerful toolkit for building, managing, and composing hierarchical prompts.
License: MIT
Keywords: prompt,llm,templating,jinja2,prompt-engineering,ai,openai,claude,anthropic,hierarchical prompts,prompt management
Author: David Tokar
Author-email: 1413david@gmail.com
Requires-Python: >=3.10,<4.0
Classifier: Development Status :: 3 - Alpha
Classifier: Intended Audience :: Developers
Classifier: License :: OSI Approved :: MIT License
Classifier: Programming Language :: Python :: 3
Classifier: Programming Language :: Python :: 3.10
Classifier: Programming Language :: Python :: 3.11
Classifier: Programming Language :: Python :: 3.12
Classifier: Programming Language :: Python :: 3.13
Classifier: Topic :: Scientific/Engineering :: Artificial Intelligence
Classifier: Topic :: Software Development :: Libraries :: Python Modules
Classifier: Typing :: Typed
Requires-Dist: jinja2 (>=3.1.6,<4.0.0)
Project-URL: Homepage, https://github.com/DavidTokar12/PromptCraft
Project-URL: Repository, https://github.com/DavidTokar12/PromptCraft
